{
    "conditions": [
        {
            "modid": "undergarden",
            "type": "forge:mod_loaded"
        }
    ],
    "entity": "undergarden:rotling",
    "variants": [],
    "name": "entity.undergarden.rotling",
    "name_color": "#CE526A",
    "display_nbt": {},
    "gui_scale": 1,
    "gui_x_offset": 0,
    "gui_y_offset": 0,
    "gui_z_offset": 0,
    "sim_cost": 256,
    "input": {
        "item": "hostilenetworks:prediction_matrix",
        "count": 1
    },
    "base_drop": {
        "item": "minecraft:stick",
        "count": 1
    },
    "trivia": "hostilenetworks.trivia.rotling",
    "fabricator_drops": [
        {
            "item": "undergarden:utheric_shard",
            "count": 10
        }
    ],
    "tier_data": [
        6,
        54,
        354,
        1254
    ],
    "data_per_kill": [
        1,
        4,
        10,
        18
    ]
}